{
	"/": [
		"src/routes/+layout.ts",
		"src/routes/+layout.ts"
	],
	"/about": [
		"src/routes/+layout.ts"
	],
	"/create": [
		"src/routes/+layout.ts"
	],
	"/docs": [
		"src/routes/+layout.ts"
	],
	"/exchange": [
		"src/routes/exchange/+page.ts",
		"src/routes/+layout.ts"
	],
	"/import": [
		"src/routes/+layout.ts"
	],
	"/news": [
		"src/routes/+layout.ts"
	],
	"/portfolio": [
		"src/routes/+layout.ts"
	],
	"/privacy": [
		"src/routes/+layout.ts"
	],
	"/settings": [
		"src/routes/+layout.ts"
	],
	"/support": [
		"src/routes/+layout.ts"
	],
	"/terms": [
		"src/routes/+layout.ts"
	],
	"/unlock": [
		"src/routes/+layout.ts"
	],
	"/wallet": [
		"src/routes/+layout.ts"
	]
}